Metadata-Version: 2.1
Name: MaximumInscribedCircle
Version: 0.1.5
Summary: 2d max empty circle
Home-page: https://github.com/markalos/MaximumInscribedCircle
Author: markalos
Author-email: bethouself@163.com
License: UNKNOWN
Keywords: empty circle
Platform: UNKNOWN
Classifier: Development Status :: 3 - Alpha
Classifier: Intended Audience :: Developers
Classifier: Topic :: Software Development :: Build Tools
Classifier: License :: OSI Approved :: MIT License
Classifier: Programming Language :: Python :: 3
Classifier: Programming Language :: Python :: 3.4
Classifier: Programming Language :: Python :: 3.5
Classifier: Programming Language :: Python :: 3.6
Provides-Extra: test
Provides-Extra: dev
